{
    "ESG_소식": [
        {
            "id": 1,
            "title": "[외신] Bloomberg, 투자자들이 포트폴리오 기후 위험 및 기회를 평가할 수 있도록 지원하는 새로운 솔루션 출시",
            "media_name": "ESG Today",
            "link": "https://www.esgtoday.com/bloomberg-launches-new-solution-to-help-investors-assess-portfolio-climate-risks-and-opportunities/?utm_source=rss&utm_medium=rss&utm_campaign=bloomberg-launches-new-solution-to-help-investors-assess-portfolio-climate-risks-and-opportunities",
            "additional_source": null,
            "new_summary_with_insight": "Bloomberg는 금융 회사들이 포트폴리오의 기후 위험을 평가할 수 있도록 지원하는 MARS Climate 솔루션을 출시했습니다. 전문가들은 이 솔루션이 기후 변화로 인한 경제적 영향을 고려한 투자 결정을 촉진할 것으로 봅니다. 이 기술은 NGFS 기후 시나리오와 연계하여 다양한 기후 시나리오를 분석합니다.",
            "date": "2025-02-20"
        },
        {
            "id": 2,
            "title": "[외신] MSCI, Swiss Re와 협력하여 금융 부문의 기후 위험 평가 및 관리 지원",
            "media_name": "ESG Today",
            "link": "https://www.esgtoday.com/msci-swiss-re-partner-to-help-financial-sector-assess-and-manage-climate-risk/?utm_source=rss&utm_medium=rss&utm_campaign=msci-swiss-re-partner-to-help-financial-sector-assess-and-manage-climate-risk",
            "additional_source": null,
            "new_summary_with_insight": "MSCI와 Swiss Re는 금융 부문 기업들이 물리적 기후 위험을 평가하고 관리할 수 있도록 돕는 협력을 발표했습니다. 이 협력은 AI 기반의 위치 정보를 활용하여 포트폴리오의 물리적 위험에 대한 통찰을 제공합니다. 금융 기관들이 자산 수준에서 기후 위험을 깊이 있게 이해할 수 있는 기회를 제공할 것으로 예상됩니다.",
            "date": "2025-02-20"
        },
        {
            "id": 3,
            "title": "[외신] 16세 창업자가 설립한 탄소 제거 스타트업, 3백50만 달러 모금",
            "media_name": "ESG Today",
            "link": "https://www.esgtoday.com/biochar-startup-founded-by-16-year-old-raises-3-5-million-to-eliminate-1-5-million-tons-of-co2/?utm_source=rss&utm_medium=rss&utm_campaign=biochar-startup-founded-by-16-year-old-raises-3-5-million-to-eliminate-1-5-million-tons-of-co2",
            "additional_source": null,
            "new_summary_with_insight": "16세 Harper Moss가 설립한 CarbonZero.Eco는 350만 달러를 모금하여 바이오차 기반 프로젝트로 CO2 제거를 추진하고 있습니다. 전문가들은 이 기술이 농작물 수확량을 개선하고 탄소 배출을 줄이는 데 기여할 것으로 보고 있습니다. 캘리포니아의 첫 생산 사이트에서 150만 톤의 아몬드 껍질을 바이오차로 전환할 계획입니다.",
            "date": "2025-02-20"
        },
        {
            "id": 4,
            "title": "[외신] Microsoft CSO, AI가 기후 목표 달성 간극을 넓히고 해결책 제공",
            "media_name": "ESG Today",
            "link": "https://www.esgtoday.com/microsoft-cso-says-ai-widens-gap-and-offers-solutions-to-meeting-climate-goals/?utm_source=rss&utm_medium=rss&utm_campaign=microsoft-cso-says-ai-widens-gap-and-offers-solutions-to-meeting-climate-goals",
            "additional_source": null,
            "new_summary_with_insight": "Microsoft의 최고 지속 가능 책임자인 Melanie Nakagawa는 AI의 급성장이 기후 목표 달성에 도전 과제를 만들었으나, 동시에 해결책도 제시한다고 밝혔습니다. 전문가들은 AI가 기후 솔루션을 가속화할 것으로 기대하고 있습니다. Microsoft는 2030년까지 탄소 네거티브를 목표로 하고 있으며, 다양한 조치를 통해 가치 사슬의 탄소 발자국을 줄이고자 하고 있습니다.",
            "date": "2025-02-20"
        }
    ],
    "AI_소식": [
        {
            "id": 1,
            "title": "비-로보틱스, 서빙로봇 이어 청소로봇까지… 서비스 로봇 시장 확대",
            "media_name": "에너지경제",
            "link": "https://www.ekn.kr/web/view.php?key=20250220028498257",
            "additional_source": null,
            "new_summary_with_insight": "비-로보틱스가 지능형 청소 솔루션을 제공하는 스마트 클리닝 로봇을 출시했습니다. 서비스 로봇 시장의 확대를 통해 생활 속 자동화 청소 솔루션의 필요성이 증가할 것으로 보입니다. 이 기술은 서빙 로봇에서 쌓은 노하우를 바탕으로 개발되었습니다.",
            "date": "2025-02-21"
        },
        {
            "id": 2,
            "title": "네이버가 찜한 자율주행 스타트업…웨어러블AI, 시드투자 유치",
            "media_name": "머니투데이",
            "link": "http://news.mt.co.kr/mtview.php?no=2025022015571383963",
            "additional_source": null,
            "new_summary_with_insight": "네이버 D2SF가 AI 기반 자율주행 스타트업 웨어러블AI에 시드 투자를 단행했습니다. 전문가들은 이 기술이 클라우드가 아닌 디바이스에서 데이터를 처리해 맞춤형 솔루션을 제공할 것으로 예상합니다. 이는 자율주행 기술의 새로운 발전을 의미할 수 있습니다.",
            "date": "2025-02-21"
        },
        {
            "id": 3,
            "title": "엘리스클라우드, 딥시크 R1·메타 라마 등 AI모델 구동환경 제공",
            "media_name": "머니투데이",
            "link": "http://news.mt.co.kr/mtview.php?no=2025022014144515595",
            "additional_source": null,
            "new_summary_with_insight": "엘리스클라우드가 다양한 AI 모델의 구동환경을 제공하며, AI 연구와 개발의 새로운 장을 열고 있습니다. 전문가들은 이 클라우드가 AI 모델의 효율적인 구현에 기여할 수 있다고 보고 있습니다. 특히 엔비디아 H100 등의 최신 하드웨어를 활용해 성능을 최적화하고 있습니다.",
            "date": "2025-02-21"
        },
        {
            "id": 4,
            "title": "소형로봇으로 물류 작업속도↑…레인보우로보틱스-테크타카 맞손",
            "media_name": "머니투데이",
            "link": "http://news.mt.co.kr/mtview.php?no=2025022016482861617",
            "additional_source": null,
            "new_summary_with_insight": "레인보우로보틱스와 테크타카가 물류 로봇 시장 진출을 위해 협력하며, 물류센터의 운영 효율성을 극대화할 계획입니다. 전문가들은 이 협력이 고객사의 비용 절감과 출고 효율성 향상에 기여할 것으로 예상합니다. 이는 글로벌 물류 자동화 시장의 중요한 전환점이 될 수 있습니다.",
            "date": "2025-02-21"
        }
    ]
}